sdg_io/__init__.py
sdg_io/crc.py
sdg_io/slip.py
sdg_io/tests.py
sdg_io/uart.py
sdg_io/utils.py
sdg_io/virtual.py
sdg_io-3.3.dist-info/LICENSE
sdg_io-3.3.dist-info/METADATA
sdg_io-3.3.dist-info/WHEEL
sdg_io-3.3.dist-info/top_level.txt
sdg_io-3.3.dist-info/RECORD
