Metadata-Version: 2.1
Name: sdg-io
Version: 3.3
Summary: protocols stack over pyserial (slip + crc16)
Author: chernecov_ev
Author-email: chernecov.ev@gmail.com
Classifier: Programming Language :: Python :: 3
Classifier: License :: OSI Approved :: MIT License
Classifier: Operating System :: OS Independent
Requires-Python: >=3.6
License-File: LICENSE
Requires-Dist: wheel
Requires-Dist: pyserial
Requires-Dist: crcmod
Requires-Dist: sdg-utils >=1.0
